MANIFEST.in
README.rst
setup.py
freegames/__init__.py
freegames/__main__.py
freegames/ant.py
freegames/bagels.py
freegames/bounce.py
freegames/button.py
freegames/cannon.py
freegames/car.gif
freegames/connect.py
freegames/crypto.py
freegames/fidget.py
freegames/flappy.py
freegames/guess.py
freegames/landscape.gif
freegames/life.py
freegames/maze.py
freegames/memory.py
freegames/minesweeper.py
freegames/pacman.py
freegames/paint.py
freegames/pong.py
freegames/savedata.py
freegames/simonsays.py
freegames/snake.py
freegames/tictactoe.py
freegames/tiles.py
freegames/tron.py
freegames/utils.py
freegames/sounds/bomb.wav
freegames/sounds/click.wav
freegames/sounds/eat.wav
freegames/sounds/get_points.wav
freegames/sounds/hit.wav
freegames/sounds/lose.wav
freegames/sounds/tile.wav
freegames/sounds/win.wav
freegames_extended.egg-info/PKG-INFO
freegames_extended.egg-info/SOURCES.txt
freegames_extended.egg-info/dependency_links.txt
freegames_extended.egg-info/top_level.txt